deutsche_bahn_api/__init__.py
deutsche_bahn_api/api_authentication.py
deutsche_bahn_api/deutsche_bahn_api.py
deutsche_bahn_api/message.py
deutsche_bahn_api/station.py
deutsche_bahn_api/station_helper.py
deutsche_bahn_api/timetable_helper.py
deutsche_bahn_api/train.py
deutsche_bahn_api/train_changes.py
deutsche_bahn_api/static/message_codes.json
deutsche_bahn_api/static/train_stations_list.json
deutsche_bahn_api-1.1.0.dist-info/licenses/LICENSE
deutsche_bahn_api-1.1.0.dist-info/METADATA
deutsche_bahn_api-1.1.0.dist-info/WHEEL
deutsche_bahn_api-1.1.0.dist-info/top_level.txt
deutsche_bahn_api-1.1.0.dist-info/RECORD
