Metadata-Version: 2.4
Name: deutsche-bahn-api
Version: 1.1.0
Summary: A small package to work with the Deutsche Bahn timetables api
Home-page: https://github.com/Tutorialwork/deutsche_bahn_api
Author: Tutorialwork
Author-email: mail@manuelschuler.dev
Classifier: Programming Language :: Python :: 3
Classifier: License :: OSI Approved :: MIT License
Classifier: Operating System :: OS Independent
License-File: LICENSE
Requires-Dist: mpu
Requires-Dist: requests
Dynamic: author
Dynamic: author-email
Dynamic: classifier
Dynamic: description
Dynamic: description-content-type
Dynamic: home-page
Dynamic: license-file
Dynamic: requires-dist
Dynamic: summary
